ord_rxn_converter/__init__.py
ord_rxn_converter/conditions_module.py
ord_rxn_converter/dataset_module.py
ord_rxn_converter/identifiers_module.py
ord_rxn_converter/inputs_module.py
ord_rxn_converter/metadata_module.py
ord_rxn_converter/notes_observations_module.py
ord_rxn_converter/outcomes_module.py
ord_rxn_converter/setup_module.py
ord_rxn_converter/utility_functions_module.py
ord_rxn_converter/workups_module.py
ord_rxn_converter-0.1.4.dist-info/licenses/LICENSE
ord_rxn_converter-0.1.4.dist-info/METADATA
ord_rxn_converter-0.1.4.dist-info/WHEEL
ord_rxn_converter-0.1.4.dist-info/top_level.txt
ord_rxn_converter-0.1.4.dist-info/RECORD
