Metadata-Version: 2.4
Name: ord_rxn_converter
Version: 0.1.4
Summary: Package for extracting chemical reaction serialized (Google Protocol Buffers mechanism) in Open Reaction Database (ORD) schema to relational database (RDB) and Resource Descriptive Framework (RDF).
Author-email: "Quynh D. Tran" <qdt@case.edu>, Ethan Tobey <emt101@case.edu>, Holly Schreiber <hls92@case.edu>, "Laura S. Bruckman" <lsh41@case.edu>, "Roger H. French" <rxf131@case.edu>
License: MIT
Project-URL: Homepage, https://github.com/cwru-sdle/ord_rxn_converter
Project-URL: Documentation, https://ord-rxn-converter.readthedocs.io/
Project-URL: Repository, https://github.com/cwru-sdle/ord_rxn_converter
Project-URL: Bug Tracker, https://github.com/cwru-sdle/ord_rxn_converter/issues
Project-URL: Changelog, https://github.com/cwru-sdle/ord_rxn_converter/blob/main/CHANGELOG.md
Keywords: chemistry,ord,open-reaction-database,machine-learning,cheminformatics,reaction-data
Classifier: Programming Language :: Python :: 3
Classifier: Operating System :: OS Independent
Requires-Python: >=3.7
License-File: LICENSE
Requires-Dist: ord_schema
Requires-Dist: protobuf
Requires-Dist: pandas
Requires-Dist: rdkit
Provides-Extra: docs
Requires-Dist: sphinx>=4.0; extra == "docs"
Requires-Dist: sphinx-rtd-theme; extra == "docs"
Requires-Dist: sphinx-autodoc-typehints; extra == "docs"
Requires-Dist: myst-parser; extra == "docs"
Provides-Extra: dev
Requires-Dist: pytest; extra == "dev"
Requires-Dist: black; extra == "dev"
Requires-Dist: flake8; extra == "dev"
Requires-Dist: mypy; extra == "dev"
Provides-Extra: all
Requires-Dist: ord_rxn_converter[dev,docs]; extra == "all"
Dynamic: license-file
